{
  "stageToLoad": "town1",
  "townsVisited": [
    "Littleroot Town",
    "Littleroot Town",
    "Littleroot Town",
    "Littleroot Town",
    "Littleroot Town",
    "Littleroot Town"
  ],
  "player": {
    "name": "Ash",
    "belt": [
      {
        "storage": {
          "name": "Jeff",
          "level": 1,
          "type": "normal",
          "moves": [
            "Tackle",
            "Tail Whip"
          ],
          "hitPoints": {
            "current": 10,
            "max": 10
          },
          "attack": {
            "current": 15,
            "max": 15
          },
          "defence": {
            "current": 11,
            "max": 11
          },
          "speed": {
            "current": null,
            "max": null
          },
          "accuracy": {
            "current": 100,
            "max": 100
          },
          "catchDifficulty": 2,
          "xpThreshold": 4,
          "xp": 1,
          "activeEffects": {},
          "id": "b8fe8942-1fa1-478d-8ad0-01e5d1cfbdbc",
          "species": "Rattata",
          "art": "\n        ⠀⠀⠀⠀⠀⠀⠀⠀⠀⠀⠀⠀⠀⠀⠀⠀⠀⠀⠀⠀⠀⠀⠀⠀⠀⠀⣠⣴⣦⣤⣄⡀⠀⠀⠀⠀⠀⠀⠀⠀⠀⠀⠀⠀\n        ⠀⠀⠀⠀⠀⠀⠀⠀⠀⠀⠀⠀⠀⠀⠀⠀⠀⠀⠀⠀⠀⠀⠀⠀⠀⠀⣿⣿⡯⣭⣟⢿⣷⣄⠀⠀⠀⠀⠀⠀⠀⠀⠀⠀\n        ⠀⠀⠀⠀⠀⠀⠀⠀⠀⠀⠀⠀⠀⠀⠀⠀⠀⠀⠀⠀⠀⠀⠀⠀⠀⠀⠙⢿⣿⣿⣿⡏⠻⢿⣷⣄⠀⠀⠀⠀⠀⠀⠀⠀\n        ⠀⠀⠀⠀⠀⠀⠀⠀⠀⠀⠀⠀⠀⠀⠀⠀⠀⠀⠀⠀⠀⠀⠀⠀⠀⠀⠀⠀⠉⠉⠉⠁⠀⠀⠉⢿⣦⠀⠀⠀⠀⠀⠀⠀\n        ⠀⠀⠀⠀⠀⠀⠀⠀⠀⠀⠀⢀⣞⢷⣦⡄⠀⠀⠀⠀⠀⠀⠀⠀⠀⠀⠀⠀⠀⠀⠀⠀⠀⠀⠀⠀⢻⡆⠀⠀⠀⠀⠀⠀\n        ⠀⠀⠀⠀⠀⠀⠀⠀⠀⠀⠀⡜⣾⡟⣿⣿⠀⠀⠀⠀⠀⠀⠀⠀⣀⣠⣤⣤⡄⠀⠀⠀⠀⠀⠀⠀⠀⢿⡀⠀⠀⠀⠀⠀\n        ⠀⠀⠀⠀⠀⠀⠀⠀⠀⠀⠀⡗⣿⣵⣶⣿⣿⣿⣷⣶⣤⡀⣤⣾⢟⣻⣭⡽⣷⠀⠀⠀⠀⠀⠀⠀⠀⠈⡇⠀⠀⠀⠀⠀\n        ⠀⠀⠀⠀⠀⠀⠈⠒⢄⡀⢠⣾⣿⣿⣿⣿⣿⣿⣿⣿⣿⣾⣟⣵⣿⣿⣿⡇⣿⠀⠀⠀⠀⠀⠀⠀⠀⠀⡇⠀⠀⠀⠀⠀\n        ⠀⠀⠀⠀⠀⠀⠀⢀⣤⣷⣿⣿⣿⣿⣿⣿⡿⠟⣯⣯⣿⣿⣿⣼⣿⣿⣿⣧⡟⢀⣠⣤⣶⣦⣤⣀⠀⢀⡇⠀⠀⠀⠀⠀\n        ⠀⠀⠀⠀⠀⠀⠀⢸⣿⣿⣿⣿⣿⣿⣟⣁⣧⢦⣿⢯⣿⣿⠿⣿⣟⣻⣟⡾⣳⣶⣿⣿⣿⣿⣿⣿⣷⡼⠃⠀⠀⠀⠀⠀\n        ⠀⠀⠀⠀⠀⠀⠀⠀⣝⣻⣿⣿⢟⢿⣿⣿⣿⣿⣿⣯⢽⣿⣿⣖⣒⣒⣶⣶⣿⣿⣿⣿⣽⣿⣿⣿⣿⣿⠀⠀⠀⠀⠀⠀\n        ⠀⠀⠀⠀⢀⣠⣤⣶⣿⢿⣿⢯⢿⣷⣝⢿⣿⣿⣿⣿⣿⣿⣿⡿⣿⣿⣿⣿⣿⣿⣿⣿⣿⣿⣿⣿⣿⣿⡇⠀⠀⠀⠀⠀\n        ⠀⠀⠈⣩⣿⣽⣿⣿⣽⣹⣯⣿⣷⡹⢯⣶⣝⢿⣿⣿⣿⣿⣟⣽⣿⣿⣿⣿⢿⣿⣿⣿⣿⡿⣿⣿⣿⣿⣷⡀⠀⠀⠀⠀\n        ⠀⠀⠈⠉⠈⠉⠀⠀⠀⠀⠀⠀⠀⠈⣿⣿⣿⢹⣿⡿⠿⢿⣾⣿⣿⣿⣿⢯⣿⣿⣿⣿⣿⣿⡻⣿⣿⣿⣿⣿⣤⣀⠀⠀\n        ⠀⠀⠀⠀⠀⠀⠀⠀⠀⠀⠀⠀⠀⠰⢿⣿⣿⠟⠋⠀⢠⣿⣿⣿⣿⣿⡃⣽⣛⣛⠛⠛⠋⠁⠀⠉⠻⠿⣿⣿⠿⣿⠀⠀\n        ⠀⠀⠀⠀⠀⠀⠀⠀⠀⠀⠀⠀⠀⠀⠀⠀⠀⠀⠀⢠⣿⣿⣿⣿⡿⠱⠛⠕⠛⠁⠀⠀⠀⠀⠀⠀⠀⢀⣴⣿⣿⡿⠀⠀\n        ⠀⠀⠀⠀⠀⠀⠀⠀⠀⠀⠀⠀⠀⠀⠀⠀⠀⢀⢴⣾⣿⣿⡿⠋⠀⠀⠀⠀⠀⠀⠀⠀⠀⠀⠀⠀⠀⠉⡟⢫⠟⠁⠀⠀\n        ⠀⠀⠀⠀⠀⠀⠀⠀⠀⠀⠀⠀⠀⠀⠀⠀⠀⠠⠟⠩⠟⠁⠀⠀⠀⠀⠀⠀⠀⠀⠀⠀⠀⠀⠀⠀⠀⠀⠀⠀⠀⠀⠀⠀"
        },
        "ballType": {
          "name": "Poke",
          "catchRate": 1
        },
        "price": 200
      },
      {
        "storage": {
          "name": "Charmander",
          "level": 1,
          "type": "fire",
          "moves": [
            "Scratch",
            "Growl",
            "Fly"
          ],
          "hitPoints": {
            "current": 10,
            "max": 10
          },
          "attack": {
            "current": 15,
            "max": 15
          },
          "defence": {
            "current": 12,
            "max": 12
          },
          "speed": {
            "current": null,
            "max": null
          },
          "accuracy": {
            "current": 100,
            "max": 100
          },
          "catchDifficulty": 5,
          "xpThreshold": 4,
          "xp": 3,
          "activeEffects": {
            "Poison Sting": {
              "status": "poisoned",
              "statusChance": "0.2"
            },
            "Poison Powder": {
              "status": "poisoned",
              "statusChance": "1"
            }
          },
          "id": "79e0e098-51a6-47d8-8dbd-3c68fb3160dd",
          "species": "Charmander",
          "evolvesTo": {
            "species": "Charmeleon",
            "level": 16
          },
          "art": "\n        ⠀⠀⠀⠀⠀⠀⠀⠀⠀⠀⠀⠀⢀⣠⣤⣶⣶⣶⣤⣀⠀⠀⠀⠀⠀⠀⠀⠀⠀⠀⠀⠀⠀⠀⠀⠀⠀⠀⠀⠀⠀⠀⠀⠀⠀⠀⠀⠀\n        ⠀⠀⠀⠀⠀⠀⠀⠀⠀⠀⢠⣾⣿⣿⣿⣿⣿⣿⣿⣿⣷⡄⠀⠀⠀⠀⠀⠀⠀⠀⠀⠀⠀⠀⠀⠀⠀⠀⠀⠀⠀⠀⠀⠀⠀⠀⠀⠀\n        ⠀⠀⠀⠀⠀⠀⠀⠀⠀⣰⣿⣿⣿⣿⣿⣿⣿⣿⣿⣿⡟⠿⡆⠀⠀⠀⠀⠀⠀⠀⠀⠀⠀⠀⠀⠀⠀⠀⠀⠀⠀⠀⠀⠀⠀⠀⠀⠀\n        ⠀⠀⠀⠀⠀⠀⠀⠀⠀⣙⣏⣿⣿⣿⣿⣿⣿⣿⣶⡏⣿⠀⢳⠀⠀⠀⠀⠀⠀⠀⠀⠀⠀⠀⠀⠀⠀⠀⠀⠀⠀⠀⠀⠀⠀⠀⠀\n        ⠀⠀⠀⠀⠀⠀⠀⠀⢠⠻⢹⣿⣿⣿⣿⣿⣿⣿⣿⡇⠉⠀⠈⡇⠀⠀⠀⠀⠀⠀⠀⠀⠀⠀⠀⠀⠀⠀⠀⠀⠀⠀⠀⠀⠀⠀⠀⠀\n        ⠀⠀⠀⠀⠀⠀⠀⠀⡴⠀⣾⣿⣿⣿⣿⣿⣿⣿⣿⣇⠀⢀⣤⣿⠀⠀⠀⠀⠀⠀⠀⠀⠀⠀⠀⠀⠀⠀⠀⠀⠀⠀⠀⠀⠀⠀⠀⠀\n        ⠀⠀⠀⠀⠀⠀⠀⢀⣿⣷⣿⣿⣿⣿⣿⣿⣿⣿⣿⣿⣿⠿⢿⣿⠀⠀⠀⠀⠀⠀⠀⠀⠀⠀⠀⠀⠀⠀⠀⠀⠀⠀⠀⠀⠀⠀⠀⠀\n        ⠀⠀⠀⠀⠀⠀⠀⠀⠙⣍⠽⠻⠾⣿⡿⠿⠟⠛⠋⠉⠘⢀⣿⠇⠀⠀⠀⠀⠀⠀⠀⠀⠀⠀⠀⠀⠀⠀⠀⠀⠀⠀⠀⠀⠀⠀\n        ⠀⠀⠀⠀⠀⠀⠀⠀⠀⠀⠙⠦⣀⡀⢀⣴⣶⣶⡿⢟⣰⣿⠏⠀⠀⠀⠀⠀⠀⠀⠀⠀⠀⠀⠀⠀⠀⠀⣶⢨⣾⡀⠀⠀⠀⠀⠀⠀\n        ⠀⠀⠀⠀⠀⠀⠀⠀⠀⠀⠀⠀⠀ ⣽⣶⣶⣶⣶⣿⣿⣿⣤⣤⣄⠀⠀⠀⠀⠀⠀⠀⠀⠀⠀⠀⠀⢸⣿⣿⣿⣧⡀⠀⠀⠀⠀⠀\n        ⠀⠀⠀⠀⠀⠀⠀⠀⢀⣀⣠⣴⣾⣿⣹⣋⣵⣶⣮⣿⣿⣿⣿⣿⣿⣿⣷⣦⣄⣄⣀⡄⠀⠀⠀⠀⢀⣼⣿⡿⢈⣿⡿⠂⠀⠀⠀⠀\n        ⠀⠀⠀⠀⠀⠰⣶⣿⣿⣿⣿⣿⣿⡏⣽⣿⣿⣿⣿⣿⣮⢿⣿⣿⣿⣿⣿⣿⣿⡟⣿⣶⡂⠀⠀⢠⣾⣿⣿⣷⣾⣿⣧⡄⠀⠀⠀⠀\n        ⠀⠀⠀⠀⠀⠀⠈⠿⣿⣿⣿⣿⠛⢱⣿⣿⣿⣿⣿⣿⣿⣷⡻⣛⡟⠛⢿⠿⠛⠋⠘⠉⠀⠀⠀⠀⠙⢿⣿⣿⣿⠏⠈⠁⠀⠀⠀⠀\n        ⠀⠀⠀⠀⠀⠀⠀⠀⠀⠀⠀⠀⠀⣿⣿⣿⣿⣿⣿⣿⣿⣿⣿⣽⣿⣷⣄⠀⠀⠀⠀⠀⠀⠀⠀⠀⠀⠈⠻⠿⠿⠟⠀⠀⠀⠀⠀⠀\n        ⠀⠀⠀⠀⠀⠀⠀⠀⠀⠀⠀⠀⠀⣿⣿⣿⣿⣿⣿⣿⣿⣿⣿⡟⣿⣿⣿⣆⠀⠀⠀⠀⠀⠀⠀⠀⠀⠀⠀⣾⡇⠀⠀⠀⠀⠀⠀⠀\n        ⠀⠀⠀⠀⠀⠀⠀⠀⠀⠀⠀⠀⣠⣿⣿⣿⣿⣿⣿⣿⣿⣿⣿⣿⢛⣿⣿⣿⣧⡀⠀⠀⠀⠀⠀⠀⠀  ⡟⠀⠀⠀⠀⠀⠀⠀⠀\n        ⠀⠀⠀⠀⠀⠀⠀⠀⠀⠀⣰⣿⣿⣞⣿⣿⣿⣿⣿⣿⣿⣿⣿⣳⣿⣿⣿⣿⣿⣷⠀⠀⠀⠀⠀⠀⠀ ⡴⠀⠀⠀⠀⠀⠀⠀⠀⠀\n        ⠀⠀⠀⠀⠀⠀⠀⠀⠀⢸⣿⣿⣿⣿⣝⢿⣿⣿⣿⣿⣿⣿⣿⣻⣿⣿⣿⣿⣿⣿⣇⠀⠀⠀⠀⠀⠀⡴⠀⠀⠀⠀⠀⠀⠀⠀⠀⠀\n        ⠀⠀⠀⠀⠀⠀⠀⠀⠀⢺⣿⣿⣿⣿⣿⣷⣍⣛⠿⣿⣿⣿⣿⡛⣿⣿⣿⣿⣿⣿⣿⠀⠀⣀⣠⠶⠊⠀⠀⠀⠀⠀⠀⠀⠀⠀⠀⠀\n        ⠀⠀⠀⠀⠀⠀⠀⠀⠀⢈⠻⣿⣿⣿⣿⡟⠉⠁⠀⠀⠈⠉⠉⠁⠈⠻⣿⣿⣿⣿⣿⡎⠙⠉⠀⠀⠀⠀⠀⠀⠀⠀⠀⠀⠀⠀⠀⠀\n        ⠀⠀⠀⠀⠀⠀⠀⠠⣮⣿⣦⡙⠟⠛⠉⠁⠀⠀⠀⠀⠀⠀⠀⠀⠀⠀⢹⣿⣿⣿⡿⣿⠀⠀⠀⠀⠀⠀⠀⠀⠀⠀⠀⠀⠀⠀⠀\n        ⠀⠀⠀⠀⠀⠀⠀⠀⠀  ⠀⠀⠀⠀⠀⠀⠀⠀⠀⠀⠀⠀⠀⠀⠀⠀⠉⠑⠮⡚⠳⡍⠁⠀⠀⠀⠀⠀⠀⠀⠀⠀⠀⠀⠀⠀⠀"
        },
        "ballType": {
          "name": "Poke",
          "catchRate": 1
        },
        "price": 200
      }
    ],
    "pokemonList": [
      "Jeff",
      "Charmander"
    ],
    "currentPokeball": {
      "storage": {
        "name": "Jeff",
        "level": 1,
        "type": "normal",
        "moves": [
          "Tackle",
          "Tail Whip"
        ],
        "hitPoints": {
          "current": 10,
          "max": 10
        },
        "attack": {
          "current": 15,
          "max": 15
        },
        "defence": {
          "current": 11,
          "max": 11
        },
        "speed": {
          "current": null,
          "max": null
        },
        "accuracy": {
          "current": 100,
          "max": 100
        },
        "catchDifficulty": 2,
        "xpThreshold": 4,
        "xp": 1,
        "activeEffects": {},
        "id": "b8fe8942-1fa1-478d-8ad0-01e5d1cfbdbc",
        "species": "Rattata",
        "art": "\n        ⠀⠀⠀⠀⠀⠀⠀⠀⠀⠀⠀⠀⠀⠀⠀⠀⠀⠀⠀⠀⠀⠀⠀⠀⠀⠀⣠⣴⣦⣤⣄⡀⠀⠀⠀⠀⠀⠀⠀⠀⠀⠀⠀⠀\n        ⠀⠀⠀⠀⠀⠀⠀⠀⠀⠀⠀⠀⠀⠀⠀⠀⠀⠀⠀⠀⠀⠀⠀⠀⠀⠀⣿⣿⡯⣭⣟⢿⣷⣄⠀⠀⠀⠀⠀⠀⠀⠀⠀⠀\n        ⠀⠀⠀⠀⠀⠀⠀⠀⠀⠀⠀⠀⠀⠀⠀⠀⠀⠀⠀⠀⠀⠀⠀⠀⠀⠀⠙⢿⣿⣿⣿⡏⠻⢿⣷⣄⠀⠀⠀⠀⠀⠀⠀⠀\n        ⠀⠀⠀⠀⠀⠀⠀⠀⠀⠀⠀⠀⠀⠀⠀⠀⠀⠀⠀⠀⠀⠀⠀⠀⠀⠀⠀⠀⠉⠉⠉⠁⠀⠀⠉⢿⣦⠀⠀⠀⠀⠀⠀⠀\n        ⠀⠀⠀⠀⠀⠀⠀⠀⠀⠀⠀⢀⣞⢷⣦⡄⠀⠀⠀⠀⠀⠀⠀⠀⠀⠀⠀⠀⠀⠀⠀⠀⠀⠀⠀⠀⢻⡆⠀⠀⠀⠀⠀⠀\n        ⠀⠀⠀⠀⠀⠀⠀⠀⠀⠀⠀⡜⣾⡟⣿⣿⠀⠀⠀⠀⠀⠀⠀⠀⣀⣠⣤⣤⡄⠀⠀⠀⠀⠀⠀⠀⠀⢿⡀⠀⠀⠀⠀⠀\n        ⠀⠀⠀⠀⠀⠀⠀⠀⠀⠀⠀⡗⣿⣵⣶⣿⣿⣿⣷⣶⣤⡀⣤⣾⢟⣻⣭⡽⣷⠀⠀⠀⠀⠀⠀⠀⠀⠈⡇⠀⠀⠀⠀⠀\n        ⠀⠀⠀⠀⠀⠀⠈⠒⢄⡀⢠⣾⣿⣿⣿⣿⣿⣿⣿⣿⣿⣾⣟⣵⣿⣿⣿⡇⣿⠀⠀⠀⠀⠀⠀⠀⠀⠀⡇⠀⠀⠀⠀⠀\n        ⠀⠀⠀⠀⠀⠀⠀⢀⣤⣷⣿⣿⣿⣿⣿⣿⡿⠟⣯⣯⣿⣿⣿⣼⣿⣿⣿⣧⡟⢀⣠⣤⣶⣦⣤⣀⠀⢀⡇⠀⠀⠀⠀⠀\n        ⠀⠀⠀⠀⠀⠀⠀⢸⣿⣿⣿⣿⣿⣿⣟⣁⣧⢦⣿⢯⣿⣿⠿⣿⣟⣻⣟⡾⣳⣶⣿⣿⣿⣿⣿⣿⣷⡼⠃⠀⠀⠀⠀⠀\n        ⠀⠀⠀⠀⠀⠀⠀⠀⣝⣻⣿⣿⢟⢿⣿⣿⣿⣿⣿⣯⢽⣿⣿⣖⣒⣒⣶⣶⣿⣿⣿⣿⣽⣿⣿⣿⣿⣿⠀⠀⠀⠀⠀⠀\n        ⠀⠀⠀⠀⢀⣠⣤⣶⣿⢿⣿⢯⢿⣷⣝⢿⣿⣿⣿⣿⣿⣿⣿⡿⣿⣿⣿⣿⣿⣿⣿⣿⣿⣿⣿⣿⣿⣿⡇⠀⠀⠀⠀⠀\n        ⠀⠀⠈⣩⣿⣽⣿⣿⣽⣹⣯⣿⣷⡹⢯⣶⣝⢿⣿⣿⣿⣿⣟⣽⣿⣿⣿⣿⢿⣿⣿⣿⣿⡿⣿⣿⣿⣿⣷⡀⠀⠀⠀⠀\n        ⠀⠀⠈⠉⠈⠉⠀⠀⠀⠀⠀⠀⠀⠈⣿⣿⣿⢹⣿⡿⠿⢿⣾⣿⣿⣿⣿⢯⣿⣿⣿⣿⣿⣿⡻⣿⣿⣿⣿⣿⣤⣀⠀⠀\n        ⠀⠀⠀⠀⠀⠀⠀⠀⠀⠀⠀⠀⠀⠰⢿⣿⣿⠟⠋⠀⢠⣿⣿⣿⣿⣿⡃⣽⣛⣛⠛⠛⠋⠁⠀⠉⠻⠿⣿⣿⠿⣿⠀⠀\n        ⠀⠀⠀⠀⠀⠀⠀⠀⠀⠀⠀⠀⠀⠀⠀⠀⠀⠀⠀⢠⣿⣿⣿⣿⡿⠱⠛⠕⠛⠁⠀⠀⠀⠀⠀⠀⠀⢀⣴⣿⣿⡿⠀⠀\n        ⠀⠀⠀⠀⠀⠀⠀⠀⠀⠀⠀⠀⠀⠀⠀⠀⠀⢀⢴⣾⣿⣿⡿⠋⠀⠀⠀⠀⠀⠀⠀⠀⠀⠀⠀⠀⠀⠉⡟⢫⠟⠁⠀⠀\n        ⠀⠀⠀⠀⠀⠀⠀⠀⠀⠀⠀⠀⠀⠀⠀⠀⠀⠠⠟⠩⠟⠁⠀⠀⠀⠀⠀⠀⠀⠀⠀⠀⠀⠀⠀⠀⠀⠀⠀⠀⠀⠀⠀⠀"
      },
      "ballType": {
        "name": "Poke",
        "catchRate": 1
      },
      "price": 200
    },
    "isPlayer": true,
    "inventory": {
      "Money": 400,
      "Poke Ball": 2,
      "Antidote": 1
    }
  },
  "PC": []
}